{
  "type": "FeatureCollection",
  "features": [
    {
      "type": "Feature",
      "properties": {},
      "geometry": {
        "coordinates": [
          [
            [
              -72.57165201673892,
              -37.46146146342353
            ],
            [
              -72.57176941531912,
              -37.46440843174132
            ],
            [
              -72.56796129888598,
              -37.464577325616155
            ],
            [
              -72.56780721324961,
              -37.46160124320196
            ],
            [
              -72.57165201673892,
              -37.46146146342353
            ]
          ]
        ],
        "type": "Polygon"
      }
    }
  ]
}